pyVersioning/AppVeyor.py
pyVersioning/CIService.py
pyVersioning/CLI.py
pyVersioning/Configuration.py
pyVersioning/GitHub.py
pyVersioning/GitLab.py
pyVersioning/Travis.py
pyVersioning/__init__.py
pyVersioning/py.typed
pyversioning-0.18.2.dist-info/licenses/LICENSE.md
pyversioning-0.18.2.dist-info/METADATA
pyversioning-0.18.2.dist-info/WHEEL
pyversioning-0.18.2.dist-info/entry_points.txt
pyversioning-0.18.2.dist-info/top_level.txt
pyversioning-0.18.2.dist-info/RECORD
